k3cgrouparch/__init__.py
k3cgrouparch/account.py
k3cgrouparch/blkio.py
k3cgrouparch/cgroup_manager.py
k3cgrouparch/cgroup_util.py
k3cgrouparch/communicate.py
k3cgrouparch/cpu.py
k3cgrouparch/manager.py
k3cgrouparch/model.py
k3cgrouparch/synopsis.py
k3cgrouparch/util.py
k3cgrouparch-0.1.3.dist-info/licenses/LICENSE
k3cgrouparch-0.1.3.dist-info/METADATA
k3cgrouparch-0.1.3.dist-info/WHEEL
k3cgrouparch-0.1.3.dist-info/top_level.txt
k3cgrouparch-0.1.3.dist-info/RECORD
